<PAMDataset>
  <PAMRasterBand band="1">
    <Histograms>
      <HistItem>
        <HistMin>0</HistMin>
        <HistMax>65535</HistMax>
        <BucketCount>256</BucketCount>
        <IncludeOutOfRange>1</IncludeOutOfRange>
        <Approximate>0</Approximate>
        <HistCounts>2000|520|615|635|649|667|692|788|1281|1585|1456|1535|2040|2609|3499|4816|6009|7730|8875|10360|11914|13349|14626|17252|19077|21499|24802|28237|32061|34423|38171|41292|46450|48652|51585|54154|57122|60551|61122|62605|63340|63815|66471|65064|64478|64103|65558|62720|61739|60423|59687|60329|57494|56592|54821|55559|52437|50897|49137|47693|46736|43901|42391|40811|39088|39002|36244|35148|34029|33954|31695|30655|30027|28342|28340|26691|25371|24099|23318|23005|21505|20112|19145|18567|17200|16606|15780|15012|14677|13591|12676|12315|11619|11305|10463|10143|9979|9779|9135|8864|8395|7883|7567|6885|6719|6191|6057|5490|5172|4989|4700|4654|4455|4310|4317|4196|4104|3573|3436|3271|3427|3062|2991|2899|2789|2763|2580|2714|2661|2584|2538|2284|2192|2045|2055|1973|1849|1828|1784|1706|1589|1348|1320|1294|1272|1161|1106|993|1000|955|907|895|848|860|837|771|738|756|684|630|543|492|389|344|286|244|242|221|220|165|159|110|98|69|73|45|41|23|14|11|14|10|7|7|5|7|7|9|1|5|5|7|5|3|1|1|2|4|6|5|3|5|3|4|1|2|3|2|5|3|2|2|0|2|1|1|1|1|0|3|1|1|1|0|1|2|0|0|2|1|0|1|0|0|0|0|0|1|1|0|0|0|0|0|1|0|0|0|0|0|0|0|0|0|0|9</HistCounts>
      </HistItem>
    </Histograms>
    <Metadata>
      <MDI key="STATISTICS_COUNT">3100000.000000</MDI>
      <MDI key="STATISTICS_COVARIANCES">38751786.94659933,0</MDI>
      <MDI key="STATISTICS_EXCLUDEDVALUES"></MDI>
      <MDI key="STATISTICS_MAXIMUM">65535</MDI>
      <MDI key="STATISTICS_MEAN">14522.25165</MDI>
      <MDI key="STATISTICS_MEDIAN">13107.000000</MDI>
      <MDI key="STATISTICS_MINIMUM">0</MDI>
      <MDI key="STATISTICS_SKIPFACTORX">1</MDI>
      <MDI key="STATISTICS_SKIPFACTORY">1</MDI>
      <MDI key="STATISTICS_STDDEV">6225.0933283445</MDI>
    </Metadata>
  </PAMRasterBand>
  <PAMRasterBand band="2">
    <Histograms>
      <HistItem>
        <HistMin>-0.5</HistMin>
        <HistMax>1.5</HistMax>
        <BucketCount>2</BucketCount>
        <IncludeOutOfRange>1</IncludeOutOfRange>
        <Approximate>0</Approximate>
        <HistCounts>0|3100000</HistCounts>
      </HistItem>
    </Histograms>
    <Metadata>
      <MDI key="STATISTICS_COUNT">3100000.000000</MDI>
      <MDI key="STATISTICS_COVARIANCES">0,0</MDI>
      <MDI key="STATISTICS_EXCLUDEDVALUES"></MDI>
      <MDI key="STATISTICS_MAXIMUM">1</MDI>
      <MDI key="STATISTICS_MEAN">1</MDI>
      <MDI key="STATISTICS_MEDIAN">1.000000</MDI>
      <MDI key="STATISTICS_MINIMUM">1</MDI>
      <MDI key="STATISTICS_SKIPFACTORX">1</MDI>
      <MDI key="STATISTICS_SKIPFACTORY">1</MDI>
      <MDI key="STATISTICS_STDDEV">0</MDI>
    </Metadata>
  </PAMRasterBand>
</PAMDataset>
